natasy/__init__.py
natasy/optimization.py
natasy/data_preparation/__init__.py
natasy/data_preparation/cross_validation.py
natasy/data_preparation/dataset.py
natasy/neural_network/__init__.py
natasy/neural_network/activations.py
natasy/neural_network/initializations.py
natasy/neural_network/network.py
natasy/neural_network/layers/__init__.py
natasy/neural_network/layers/convLayer.py
natasy/neural_network/layers/fullyconnectedlayer.py
natasy/neural_network/layers/hiddenlayer.py
natasy/neural_network/layers/neuralnetworklayer.py
natasy/neural_network/layers/outputlayer.py
natasy/neural_network/layers/softmax_with_xentropy.py
Natasy-0.0.1.dist-info/LICENSE
Natasy-0.0.1.dist-info/METADATA
Natasy-0.0.1.dist-info/WHEEL
Natasy-0.0.1.dist-info/top_level.txt
Natasy-0.0.1.dist-info/RECORD
