Metadata-Version: 2.1
Name: Natasy
Version: 0.0.1
Summary: A machine learning engine designed and developed to be both easy to use and source code readable.
Home-page: https://github.com/disooqi/Natasy
Author: Mohamed
Author-email: mohamed@eldesouki.com
License: UNKNOWN
Project-URL: Bug Tracker, https://github.com/disooqi/Natasy/issues
Platform: UNKNOWN
Classifier: Programming Language :: Python :: 3
Classifier: License :: OSI Approved :: Academic Free License (AFL)
Classifier: Operating System :: OS Independent
Requires-Python: >=3.6
License-File: LICENSE
Requires-Dist: numpy (>=1.21.2)
Requires-Dist: scipy (>=1.7.1)
Requires-Dist: tqdm (>=4.62.2)
Provides-Extra: tests
Requires-Dist: pytest ; extra == 'tests'
